MANIFEST.in
setup.py
xsiftx/__init__.py
xsiftx/command_line.py
xsiftx/config.py
xsiftx/store.py
xsiftx/tools.py
xsiftx/util.py
xsiftx/web.py
xsiftx.egg-info/PKG-INFO
xsiftx.egg-info/SOURCES.txt
xsiftx.egg-info/dependency_links.txt
xsiftx.egg-info/entry_points.txt
xsiftx.egg-info/not-zip-safe
xsiftx.egg-info/requires.txt
xsiftx.egg-info/top_level.txt
xsiftx/lti/__init__.py
xsiftx/lti/decorators.py
xsiftx/lti/oauthstore.py
xsiftx/lti/util.py
xsiftx/lti/static/lti/css/index.css
xsiftx/lti/static/lti/js/index.js
xsiftx/lti/templates/lti/index.html
xsiftx/lti/templates/lti/lti_error.html
xsiftx/sifters/__init__.py
xsiftx/sifters/__init__.pyc
xsiftx/sifters/compute_grades
xsiftx/sifters/content_statistics
xsiftx/sifters/copy_file
xsiftx/sifters/dump_grades
xsiftx/sifters/remote_grades
xsiftx/sifters/test_sifters
xsiftx/sifters/xqanalyze
xsiftx/tests/__init__.py
xsiftx/tests/test_command.py
xsiftx/tests/test_lti.py
xsiftx/tests/test_util.py
xsiftx/tests/util.py