Metadata-Version: 1.1
Name: xsiftx
Version: 0.7.2
Summary: Program for running data collection scripts against courses and putting the results in the instructor dashboard of the local edx-platform instance
Home-page: http://github.com/mitocw/xsiftx
Author: MITx
Author-email: mitx-devops@mit.edu
License: GNU General Public License v3 (GPLv3)
Platform: UNKNOWN
Classifier: Development Status :: 3 - Alpha
Classifier: Environment :: Console
Classifier: Intended Audience :: Developers
Classifier: Intended Audience :: Education
Classifier: License :: OSI Approved :: GNU General Public License v3 (GPLv3)
Classifier: Operating System :: OS Independent
Classifier: Programming Language :: Python
Classifier: Programming Language :: Python :: 2
Classifier: Programming Language :: Python :: 2.7
